validator_for_postcodes/__init__.py
validator_for_postcodes/countries_.py
validator_for_postcodes/utils.py
validator_for_postcodes/validator.py
validator_for_postcodes/countries/__init__.py
validator_for_postcodes/countries/uk/__init__.py
validator_for_postcodes/countries/uk/data.py
validator_for_postcodes/countries/uk/postcode.py
validator_for_postcodes/countries/uk/regex_.py
validator_for_postcodes/countries/uk/static_cases.py
validator_for_postcodes/countries/uk/utils.py
validator_for_postcodes/countries/uk/validator.py
validator_for_postcodes-0.1.3.dist-info/licenses/LICENSE
validator_for_postcodes-0.1.3.dist-info/METADATA
validator_for_postcodes-0.1.3.dist-info/WHEEL
validator_for_postcodes-0.1.3.dist-info/top_level.txt
validator_for_postcodes-0.1.3.dist-info/RECORD
